<?xml version='1.1' encoding='UTF-8'?>
<com.cloudbees.plugins.credentials.SystemCredentialsProvider plugin="credentials@1214.v1de940103927">
  <domainCredentialsMap class="hudson.util.CopyOnWriteMap$Hash">
    <entry>
      <com.cloudbees.plugins.credentials.domains.Domain>
        <specifications/>
      </com.cloudbees.plugins.credentials.domains.Domain>
      <java.util.concurrent.CopyOnWriteArrayList>
        <com.cloudbees.plugins.credentials.impl.UsernamePasswordCredentialsImpl>
          <scope>GLOBAL</scope>
          <id>global</id>
          <description></description>
          <username>global</username>
          <password>{AQAAABAAAAAQbt1ixIaMpJar0hiYA0OFcSxam/OZAu5iAx3ElpkRqhI=}</password>
          <usernameSecret>false</usernameSecret>
        </com.cloudbees.plugins.credentials.impl.UsernamePasswordCredentialsImpl>
        <com.cloudbees.plugins.credentials.impl.UsernamePasswordCredentialsImpl>
          <scope>SYSTEM</scope>
          <id>system</id>
          <description></description>
          <username>system</username>
          <password>{AQAAABAAAAAQ2+z16//qeYL1uNEe+DhNJdmjpp+szqOVnOHwxj/+ytk=}</password>
          <usernameSecret>false</usernameSecret>
        </com.cloudbees.plugins.credentials.impl.UsernamePasswordCredentialsImpl>
        <org.jenkinsci.plugins.plaincredentials.impl.StringCredentialsImpl plugin="plain-credentials@143.v1b_df8b_d3b_e48">
          <scope>GLOBAL</scope>
          <id>github-nato</id>
          <description>github-nato</description>
          <secret>{AQAAABAAAAAw5C9Kaa3lRO1UgO2JXC2qJPSKC8HvrO4vodjpim685Gb5NuFbklGOdz5nF3h49PsAFaV1tzPim+wm9+/DcGr22w==}</secret>
        </org.jenkinsci.plugins.plaincredentials.impl.StringCredentialsImpl>
        <com.cloudbees.plugins.credentials.impl.UsernamePasswordCredentialsImpl>
          <scope>GLOBAL</scope>
          <id>github-nato-cred</id>
          <description>github-nato-cred</description>
          <username>Nato-G</username>
          <password>{AQAAABAAAAAwDtuIAkY+rT9JR1Frt7JH/0HkIg74odJHyWSFZA7xFicB4AeFFBjARykHeQRK0GkMMfihSO9pilnHgOZUPpS+uQ==}</password>
          <usernameSecret>false</usernameSecret>
        </com.cloudbees.plugins.credentials.impl.UsernamePasswordCredentialsImpl>
      </java.util.concurrent.CopyOnWriteArrayList>
    </entry>
  </domainCredentialsMap>
</com.cloudbees.plugins.credentials.SystemCredentialsProvider>